arbori/__init__.py
arbori/__main__.py
arbori/cli.py
arbori/io.py
arbori/tree.py
arbori-0.2.0.dist-info/LICENSE
arbori-0.2.0.dist-info/METADATA
arbori-0.2.0.dist-info/WHEEL
arbori-0.2.0.dist-info/entry_points.txt
arbori-0.2.0.dist-info/top_level.txt
arbori-0.2.0.dist-info/RECORD
