Metadata-Version: 2.1
Name: arbori
Version: 0.2.0
Summary: Create a directory structure given a simple input format.
Author-email: Harley Wilson <hi@harleyjwilson.com>
License: MIT License
Project-URL: Homepage, https://github.com/harleyjwilson/arbori
Project-URL: Bug Tracker, https://github.com/harleyjwilson/arbori/issues
Classifier: Programming Language :: Python :: 3
Classifier: License :: OSI Approved :: MIT License
Classifier: Operating System :: OS Independent
Requires-Python: >=3.12
License-File: LICENSE
Requires-Dist: click~=8.1.7
Provides-Extra: test
Requires-Dist: ruff~=0.7.1; extra == "test"
Requires-Dist: pytest~=8.3.3; extra == "test"
